farasa/__base.py
farasa/__init__.py
farasa/diacratizer.py
farasa/lemmatizer.py
farasa/ner.py
farasa/pos.py
farasa/segmenter.py
farasa/spellchecker.py
farasa/stemmer.py
farasapy-0.1.1.dist-info/METADATA
farasapy-0.1.1.dist-info/WHEEL
farasapy-0.1.1.dist-info/licenses/LICENSE
farasapy-0.1.1.dist-info/RECORD
