Metadata-Version: 2.4
Name: farasapy
Version: 0.1.1
Summary: A Python Wrapper for the well Farasa toolkit
License-File: LICENSE
Requires-Python: >=3.10
Requires-Dist: requests~=2.32
Requires-Dist: tqdm~=4.66
Provides-Extra: dev
Requires-Dist: black==24.3.0; extra == 'dev'
Requires-Dist: bleach==3.3.0; extra == 'dev'
Requires-Dist: pylint==2.5.2; extra == 'dev'
